sutherland/__init__.py
sutherland/suther.py
sutherland-0.0.1.dist-info/LICENSE
sutherland-0.0.1.dist-info/METADATA
sutherland-0.0.1.dist-info/WHEEL
sutherland-0.0.1.dist-info/top_level.txt
sutherland-0.0.1.dist-info/RECORD
