Metadata-Version: 2.1
Name: sutherland
Version: 0.0.1
Summary: Sutherland's Law for Viscosity
Home-page: https://github.com/sadicesur/sutherland.git
Author: Sadi Cesur
Author-email: cesursadi@gmail.com
License: UNKNOWN
Project-URL: Bug Tracker, https://github.com/sadicesur/sutherland.git
Platform: UNKNOWN
Classifier: Programming Language :: Python :: 3
Classifier: License :: OSI Approved :: MIT License
Classifier: Operating System :: OS Independent
Requires-Python: >=3.6
License-File: LICENSE
